mambaex/__init__.py
mambaex/__version__.py
mambaex/mambaexApp.py
mambaex/mambaexApps.py
mambaex-0.0.1a3.dist-info/LICENSE
mambaex-0.0.1a3.dist-info/METADATA
mambaex-0.0.1a3.dist-info/WHEEL
mambaex-0.0.1a3.dist-info/top_level.txt
mambaex-0.0.1a3.dist-info/RECORD
