Metadata-Version: 2.1
Name: mambaex
Version: 0.0.1a3
Summary: Python HTTP Server for Humans.
Home-page: https://mambaex.readthedocs.io
Author: Prashant Farkya
Author-email: prashant.farkya@gmail.com
License: MIT Licence
Project-URL: Documentation, https://mambaex.readthedocs.io
Project-URL: Source, https://github.com/pfarkya/mambaex
Platform: UNKNOWN
Classifier: Development Status :: 5 - Production/Stable
Classifier: Intended Audience :: Developers
Classifier: Natural Language :: English
Classifier: License :: OSI Approved :: Apache Software License
Classifier: Programming Language :: Python
Classifier: Programming Language :: Python :: 3
Classifier: Programming Language :: Python :: 3.5
Classifier: Programming Language :: Python :: 3.6
Classifier: Programming Language :: Python :: 3.7
Classifier: Programming Language :: Python :: 3.8
Classifier: Programming Language :: Python :: Implementation :: CPython
Classifier: Programming Language :: Python :: Implementation :: PyPy
Requires-Python: !=3.0.*, !=3.1.*, !=3.2.*, !=3.3.*, !=3.4.*
Requires-Dist: chardet (<3.1.0,>=3.0.2)
Requires-Dist: idna (<2.9,>=2.5)
Requires-Dist: urllib3 (!=1.25.0,!=1.25.1,<1.26,>=1.21.1)
Requires-Dist: certifi (>=2017.4.17)
Provides-Extra: security
Requires-Dist: pyOpenSSL (>=0.14) ; extra == 'security'
Requires-Dist: cryptography (>=1.3.4) ; extra == 'security'
Requires-Dist: idna (>=2.0.0) ; extra == 'security'
Provides-Extra: socks
Requires-Dist: PySocks (!=1.5.7,>=1.5.6) ; extra == 'socks'
Requires-Dist: win-inet-pton ; (sys_platform == "win32" and python_version == "2.7") and extra == 'socks'
